plotlines/__init__.py
plotlines/basis.py
plotlines/board.py
plotlines/coordinates.py
plotlines/main.py
plotlines/motif.py
plotlines/plotter.py
plotlines/schema.py
plotlines/sketch.py
plotlines/three_sixteenths.py
plotlines/tree.py
plotlines/assets/basics.css
plotlines/assets/head.toml
plotlines/assets/layout.css
plotlines/assets/object.css
plotlines/assets/words.txt
plotlines/test/__init__.py
plotlines/test/test_basis.py
plotlines/test/test_board.py
plotlines/test/test_coordinates.py
plotlines/test/test_motif.py
plotlines/test/test_plotter.py
plotlines/test/test_three_sixteenths.py
plotlines/test/test_tree.py
plotlines/test/data/inkscape_properties_n03e02.svg
plotlines/test/data/minimal_rect_n03e02.svg
plotlines/test/data/minimal_rect_n03e02.xml
plotlines/test/data/minimal_uml_n04e05.xml
plotlines/test/data/multi_uml_n04e05.xml
plotlines/test/data/spiki-demo_n51.svg
plotlines-0.5.0.dist-info/licenses/COPYING
plotlines-0.5.0.dist-info/METADATA
plotlines-0.5.0.dist-info/WHEEL
plotlines-0.5.0.dist-info/entry_points.txt
plotlines-0.5.0.dist-info/top_level.txt
plotlines-0.5.0.dist-info/RECORD
