Metadata-Version: 2.4
Name: plotlines
Version: 0.5.0
Summary: Create and display Story structure.
Author: D E Haynes
Maintainer-email: Tundish <tundish@gigeconomy.org.uk>
License-Expression: GPL-3.0-or-later
Classifier: Topic :: Multimedia
Classifier: Natural Language :: English
Classifier: Operating System :: OS Independent
Classifier: Environment :: Web Environment
Classifier: Programming Language :: Python :: 3 :: Only
Requires-Python: >=3.12
License-File: COPYING
Dynamic: license-file
